pycid/__init__.py
pycid/version.py
pycid/analyze/__init__.py
pycid/analyze/effects.py
pycid/analyze/instrumental_control_incentive.py
pycid/analyze/reasoning_patterns.py
pycid/analyze/requisite_graph.py
pycid/analyze/response_incentive.py
pycid/analyze/value_of_control.py
pycid/analyze/value_of_information.py
pycid/core/__init__.py
pycid/core/causal_bayesian_network.py
pycid/core/cid.py
pycid/core/cpd.py
pycid/core/get_paths.py
pycid/core/macid.py
pycid/core/macid_base.py
pycid/core/relevance_graph.py
pycid/examples/__init__.py
pycid/examples/simple_cbns.py
pycid/examples/simple_cids.py
pycid/examples/simple_macids.py
pycid/examples/story_cids.py
pycid/examples/story_macids.py
pycid/export/__init__.py
pycid/export/gambit.py
pycid/random/__init__.py
pycid/random/random_cid.py
pycid/random/random_cpd.py
pycid/random/random_dag.py
pycid/random/random_macid.py
pycid/random/random_macidbase.py
pycid-0.8.2.dist-info/LICENSE
pycid-0.8.2.dist-info/METADATA
pycid-0.8.2.dist-info/NOTICE
pycid-0.8.2.dist-info/WHEEL
pycid-0.8.2.dist-info/top_level.txt
pycid-0.8.2.dist-info/RECORD
