Metadata-Version: 2.1
Name: pycid
Version: 0.8.2
Summary: Causal Influence Diagram library
Home-page: https://github.com/causalincentives/pycid
Author: Causal Incentives Working Group
Author-email: james.fox@keble.ox.ac.uk
License: Apache License 2.0
Classifier: Development Status :: 3 - Alpha
Classifier: Intended Audience :: Science/Research
Classifier: License :: OSI Approved :: Apache Software License
Classifier: Operating System :: OS Independent
Classifier: Programming Language :: Python :: 3
Classifier: Topic :: Scientific/Engineering :: Artificial Intelligence
Classifier: Topic :: Scientific/Engineering :: Mathematics
Classifier: Topic :: Software Development :: Libraries
Requires-Python: >=3.7
License-File: LICENSE
License-File: NOTICE
Requires-Dist: matplotlib
Requires-Dist: networkx
Requires-Dist: numpy
Requires-Dist: pgmpy ==0.1.17
Requires-Dist: pygambit ==16.0.2
Provides-Extra: notebook
Requires-Dist: ipykernel ; extra == 'notebook'
Provides-Extra: test
Requires-Dist: flake8 ; extra == 'test'
Requires-Dist: ipykernel ; extra == 'test'
Requires-Dist: mypy ; extra == 'test'
Requires-Dist: nbconvert ; extra == 'test'
Requires-Dist: nbformat ; extra == 'test'
Requires-Dist: pep8-naming ; extra == 'test'
Requires-Dist: pytest ; extra == 'test'
